django_rick_base/__init__.py
django_rick_base/admin.py
django_rick_base/apps.py
django_rick_base/client.py
django_rick_base/manager.py
django_rick_base/models.py
django_rick_base/signals.py
django_rick_base/tests.py
django_rick_base/urls.py
django_rick_base/utils.py
django_rick_base/views.py
django_rick_base/migrations/0001_initial.py
django_rick_base/migrations/0002_remove_bothook_name_bothook_hook_name.py
django_rick_base/migrations/__init__.py
django_rick_base-0.1.0.dist-info/METADATA
django_rick_base-0.1.0.dist-info/WHEEL
django_rick_base-0.1.0.dist-info/RECORD
