Metadata-Version: 2.4
Name: django-rick-base
Version: 0.1.0
Summary: 一个基于 Django 的基础项目自用项目
Author-email: li2810081 <276069869@qq.com>
Requires-Python: >=3.8.6
Requires-Dist: cryptography>=46.0.3
Requires-Dist: django-polls>=0.2.1
Requires-Dist: django==4.2
Requires-Dist: djangorestframework>=3.15.2
Requires-Dist: drf-spectacular>=0.29.0
Requires-Dist: pycryptodome>=3.23.0
Requires-Dist: pymysql>=1.1.2
Requires-Dist: requests>=2.32.4
